{
"type": "FeatureCollection",
"name": "M8_istasyonlari",
"crs": { "type": "name", "properties": { "name": "urn:ogc:def:crs:OGC:1.3:CRS84" } },
"features": [
{ "type": "Feature", "properties": { "ISTASYON": "Mevlana", "PROJE_ADI": "M8 Bostancı - Dudullu Metro Hattı", "PROJE_ASAMA": "Mevcut Hattaki İstasyon", "HAT_TURU": "Metro", "MUDURLUK": "Anadolu Yakası Raylı Sistemler Müdürlüğü" }, "geometry": { "type": "Point", "coordinates": [ 29.153357120399999, 40.992156465 ] } },
{ "type": "Feature", "properties": { "ISTASYON": "İmes", "PROJE_ADI": "M8 Bostancı - Dudullu Metro Hattı", "PROJE_ASAMA": "Mevcut Hattaki İstasyon", "HAT_TURU": "Metro", "MUDURLUK": "Anadolu Yakası Raylı Sistemler Müdürlüğü" }, "geometry": { "type": "Point", "coordinates": [ 29.156211756400001, 41.000148127199999 ] } },
{ "type": "Feature", "properties": { "ISTASYON": "Parseller", "PROJE_ADI": "M8 Bostancı - Dudullu Metro Hattı", "PROJE_ASAMA": "Mevcut Hattaki İstasyon", "HAT_TURU": "Metro", "MUDURLUK": "Anadolu Yakası Raylı Sistemler Müdürlüğü" }, "geometry": { "type": "Point", "coordinates": [ 29.152667402199999, 41.031243352899999 ] } },
{ "type": "Feature", "properties": { "ISTASYON": "Huzur", "PROJE_ADI": "M8 Bostancı - Dudullu Metro Hattı", "PROJE_ASAMA": "Mevcut Hattaki İstasyon", "HAT_TURU": "Metro", "MUDURLUK": "Anadolu Yakası Raylı Sistemler Müdürlüğü" }, "geometry": { "type": "Point", "coordinates": [ 29.159551400400002, 41.022634420300001 ] } },
{ "type": "Feature", "properties": { "ISTASYON": "İçerenköy", "PROJE_ADI": "M8 Bostancı - Dudullu Metro Hattı", "PROJE_ASAMA": "Mevcut Hattaki İstasyon", "HAT_TURU": "Metro", "MUDURLUK": "Anadolu Yakası Raylı Sistemler Müdürlüğü" }, "geometry": { "type": "Point", "coordinates": [ 29.126424906, 40.978984539400003 ] } },
{ "type": "Feature", "properties": { "ISTASYON": "Kozyatağı", "PROJE_ADI": "M8 Bostancı - Dudullu Metro Hattı", "PROJE_ASAMA": "Mevcut Hattaki İstasyon", "HAT_TURU": "Metro", "MUDURLUK": "Anadolu Yakası Raylı Sistemler Müdürlüğü" }, "geometry": { "type": "Point", "coordinates": [ 29.099900237100002, 40.977501558299998 ] } },
{ "type": "Feature", "properties": { "ISTASYON": "Ayşe Kadın", "PROJE_ADI": "M8 Bostancı - Dudullu Metro Hattı", "PROJE_ASAMA": "Mevcut Hattaki İstasyon", "HAT_TURU": "Metro", "MUDURLUK": "Anadolu Yakası Raylı Sistemler Müdürlüğü" }, "geometry": { "type": "Point", "coordinates": [ 29.086718150900001, 40.966777471699999 ] } },
{ "type": "Feature", "properties": { "ISTASYON": "Bostancı", "PROJE_ADI": "M8 Bostancı - Dudullu Metro Hattı", "PROJE_ASAMA": "Mevcut Hattaki İstasyon", "HAT_TURU": "Metro", "MUDURLUK": "Anadolu Yakası Raylı Sistemler Müdürlüğü" }, "geometry": { "type": "Point", "coordinates": [ 29.097722504699998, 40.950963645599998 ] } },
{ "type": "Feature", "properties": { "ISTASYON": "Emin Ali Paşa", "PROJE_ADI": "M8 Bostancı - Dudullu Metro Hattı", "PROJE_ASAMA": "Mevcut Hattaki İstasyon", "HAT_TURU": "Metro", "MUDURLUK": "Anadolu Yakası Raylı Sistemler Müdürlüğü" }, "geometry": { "type": "Point", "coordinates": [ 29.093708492299999, 40.960547264200002 ] } },
{ "type": "Feature", "properties": { "ISTASYON": "Kayışdağı", "PROJE_ADI": "M8 Bostancı - Dudullu Metro Hattı", "PROJE_ASAMA": "Mevcut Hattaki İstasyon", "HAT_TURU": "Metro", "MUDURLUK": "Anadolu Yakası Raylı Sistemler Müdürlüğü" }, "geometry": { "type": "Point", "coordinates": [ 29.137730610799998, 40.9846900159 ] } },
{ "type": "Feature", "properties": { "ISTASYON": "Dudullu", "PROJE_ADI": "M8 Bostancı - Dudullu Metro Hattı", "PROJE_ASAMA": "Mevcut Hattaki İstasyon", "HAT_TURU": "Metro", "MUDURLUK": "Anadolu Yakası Raylı Sistemler Müdürlüğü" }, "geometry": { "type": "Point", "coordinates": [ 29.163287072500001, 41.015232591500002 ] } },
{ "type": "Feature", "properties": { "ISTASYON": "Küçükbakkalköy", "PROJE_ADI": "M8 Bostancı - Dudullu Metro Hattı", "PROJE_ASAMA": "Mevcut Hattaki İstasyon", "HAT_TURU": "Metro", "MUDURLUK": "Anadolu Yakası Raylı Sistemler Müdürlüğü" }, "geometry": { "type": "Point", "coordinates": [ 29.1117414468, 40.9789184865 ] } },
{ "type": "Feature", "properties": { "ISTASYON": "Modoko - Keyap", "PROJE_ADI": "M8 Bostancı - Dudullu Metro Hattı", "PROJE_ASAMA": "Mevcut Hattaki İstasyon", "HAT_TURU": "Metro", "MUDURLUK": "Anadolu Yakası Raylı Sistemler Müdürlüğü" }, "geometry": { "type": "Point", "coordinates": [ 29.161855314, 41.007187637599998 ] } }
]
}
